emora_stdm/__init__.py
emora_stdm/modules/__init__.py
emora_stdm/modules/hello_world_example.py
emora_stdm/modules/interoperability_example.py
emora_stdm/modules/macro_definition_example.py
emora_stdm/modules/multiple_components_example.py
emora_stdm/modules/natex_compilation.py
emora_stdm/modules/ontology_example.py
emora_stdm/modules/reasoning_example.py
emora_stdm/modules/sigdial_example.py
emora_stdm/modules/update_rules_example.py
emora_stdm/modules/emora/__init__.py
emora_stdm/state_transition_dialogue_manager/__init__.py
emora_stdm/state_transition_dialogue_manager/chat_flow.py
emora_stdm/state_transition_dialogue_manager/chat_flow_v2.py
emora_stdm/state_transition_dialogue_manager/composite_dialogue_flow.py
emora_stdm/state_transition_dialogue_manager/database.py
emora_stdm/state_transition_dialogue_manager/dialogue_flow.py
emora_stdm/state_transition_dialogue_manager/knowledge_base.py
emora_stdm/state_transition_dialogue_manager/macro.py
emora_stdm/state_transition_dialogue_manager/macros_common.py
emora_stdm/state_transition_dialogue_manager/memory.py
emora_stdm/state_transition_dialogue_manager/natex_common.py
emora_stdm/state_transition_dialogue_manager/natex_nlg.py
emora_stdm/state_transition_dialogue_manager/natex_nlu.py
emora_stdm/state_transition_dialogue_manager/ngrams.py
emora_stdm/state_transition_dialogue_manager/patch.py
emora_stdm/state_transition_dialogue_manager/process_wordnet_data.py
emora_stdm/state_transition_dialogue_manager/settings.py
emora_stdm/state_transition_dialogue_manager/state.py
emora_stdm/state_transition_dialogue_manager/stochastic_options.py
emora_stdm/state_transition_dialogue_manager/update_rule.py
emora_stdm/state_transition_dialogue_manager/update_rules.py
emora_stdm/state_transition_dialogue_manager/utilities.py
emora_stdm/state_transition_dialogue_manager/wordnet.py
emora_stdm/state_transition_dialogue_manager/data/__init__.py
emora_stdm/state_transition_dialogue_manager/data/wordnet.json
emora_stdm-2.0.5.dist-info/METADATA
emora_stdm-2.0.5.dist-info/WHEEL
emora_stdm-2.0.5.dist-info/top_level.txt
emora_stdm-2.0.5.dist-info/RECORD
