Metadata-Version: 2.1
Name: emora-stdm
Version: 2.0.5
Summary: Library for creating state-machine-based chatbots.
Home-page: https://github.com/emora-chat/EmoraSTDM.git
Author: James Finch
Author-email: jdfinch@emory.edu
License: UNKNOWN
Platform: UNKNOWN
Classifier: Programming Language :: Python :: 3
Classifier: License :: OSI Approved :: MIT License
Classifier: Operating System :: OS Independent
Requires-Dist: structpy (==0.3)
Requires-Dist: lark-parser
Requires-Dist: regex
Requires-Dist: nltk
Requires-Dist: importlib-resources
Requires-Dist: pytz
Requires-Dist: dill
Requires-Dist: pathos
Requires-Dist: contractions
Requires-Dist: num2words
